mallu.py
model.py
santa.py
mallu-0.1.6.dist-info/AUTHORS.txt
mallu-0.1.6.dist-info/LICENSE
mallu-0.1.6.dist-info/METADATA
mallu-0.1.6.dist-info/WHEEL
mallu-0.1.6.dist-info/top_level.txt
mallu-0.1.6.dist-info/RECORD
