Metadata-Version: 2.1
Name: mallu
Version: 0.1.6
Summary: Package for easier Machine Learning Workflow.
Home-page: https://github.com/santokalayil/mallu
Author: Santo K Thomas
Author-email: santokalayil@gmail.com
License: UNKNOWN
Platform: UNKNOWN
Classifier: License :: OSI Approved :: MIT License
Classifier: Programming Language :: Python :: 3
Classifier: Programming Language :: Python :: 3.7
Classifier: Programming Language :: Python :: 3.8
Classifier: Operating System :: OS Independent
Requires-Dist: numpy
Requires-Dist: pandas
Requires-Dist: matplotlib
Requires-Dist: scipy
Requires-Dist: seaborn
Requires-Dist: sklearn
Requires-Dist: catboost
Requires-Dist: xgboost
Requires-Dist: imblearn
Requires-Dist: lightgbm
